azchaosaws/__init__.py
azchaosaws/helpers.py
azchaosaws/utils.py
azchaosaws/waiters.py
azchaosaws/asg/__init__.py
azchaosaws/asg/actions.py
azchaosaws/ec2/__init__.py
azchaosaws/ec2/actions.py
azchaosaws/eks/__init__.py
azchaosaws/eks/actions.py
azchaosaws/elasticache/__init__.py
azchaosaws/elasticache/actions.py
azchaosaws/elb/__init__.py
azchaosaws/elb/actions.py
azchaosaws/elbv2/__init__.py
azchaosaws/elbv2/actions.py
azchaosaws/mq/__init__.py
azchaosaws/mq/actions.py
azchaosaws/rds/__init__.py
azchaosaws/rds/actions.py
aws_az_failure_chaostoolkit-0.1.10.dist-info/LICENSE
aws_az_failure_chaostoolkit-0.1.10.dist-info/METADATA
aws_az_failure_chaostoolkit-0.1.10.dist-info/NOTICE
aws_az_failure_chaostoolkit-0.1.10.dist-info/WHEEL
aws_az_failure_chaostoolkit-0.1.10.dist-info/top_level.txt
aws_az_failure_chaostoolkit-0.1.10.dist-info/RECORD
