Metadata-Version: 2.1
Name: aws-az-failure-chaostoolkit
Version: 0.1.10
Summary: Custom Chaos Toolkit extension to simulate AZ failure on AWS resources
Home-page: https://github.com/awslabs/aws-az-failure-chaostoolkit
Author: Farhan Angullia
Author-email: angullia@amazon.com
License: Apache License Version 2.0
Download-URL: https://pypi.python.org/pypi/aws-az-failure-chaostoolkit
Platform: UNKNOWN
Classifier: Development Status :: 5 - Production/Stable
Classifier: Intended Audience :: Developers
Classifier: License :: Freely Distributable
Classifier: Operating System :: OS Independent
Classifier: License :: OSI Approved :: Apache Software License
Classifier: Programming Language :: Python
Classifier: Programming Language :: Python :: 3
Classifier: Programming Language :: Python :: 3.7
Classifier: Programming Language :: Python :: 3.8
Classifier: Programming Language :: Python :: 3.9
Classifier: Programming Language :: Python :: Implementation
Classifier: Programming Language :: Python :: Implementation :: CPython
Requires-Python: >=3.7
Requires-Dist: chaostoolkit-lib >=1.1.2
Requires-Dist: logzero <2.0.0,>=1.7.0
Requires-Dist: boto3 <2.0.0,>=1.18.32
